farmer_pytorch/__init__.py
farmer_pytorch/get_annotation.py
farmer_pytorch/get_dataset.py
farmer_pytorch/get_optimization.py
farmer_pytorch/logger/__init__.py
farmer_pytorch/logger/base.py
farmer_pytorch/logger/progress_bar.py
farmer_pytorch/metrics/__init__.py
farmer_pytorch/metrics/seg_metrics.py
farmer_pytorch/readers/__init__.py
farmer_pytorch/readers/cross_val.py
farmer_pytorch/readers/read_annotation.py
farmer_pytorch/utils.py
farmer_pytorch-0.3.0.dist-info/WHEEL
farmer_pytorch-0.3.0.dist-info/METADATA
farmer_pytorch-0.3.0.dist-info/RECORD
